pyutility/__init__.py
pyutility/_windows.py
pyutility/memoryutil.py
pyutility/timeutil.py
pyutility/utility.py
tests/__init__.py
tests/func.py
tests/test_memory.py
tests/test_time.py
tests/test_utility.py
py_utility-0.1.3.dist-info/LICENSE
py_utility-0.1.3.dist-info/METADATA
py_utility-0.1.3.dist-info/WHEEL
py_utility-0.1.3.dist-info/top_level.txt
py_utility-0.1.3.dist-info/RECORD
