Metadata-Version: 1.2
Name: py-utility
Version: 0.1.3
Summary: Utility functions for managing and monitoring python resources
Home-page: https://github.com/Vipul-Cariappa/py-utility
Author: Vipul Cariappa
Author-email: vipulcariappa@gmail.com
License: MIT
Keywords: py-utility
Platform: UNKNOWN
Classifier: Development Status :: 4 - Beta
Classifier: License :: OSI Approved :: MIT License
Classifier: Operating System :: Unix
Classifier: Operating System :: Microsoft :: Windows
Classifier: Programming Language :: Python :: 3.6
Classifier: Programming Language :: Python :: 3.7
Classifier: Programming Language :: Python :: 3.8
Classifier: Programming Language :: Python :: 3.9
Requires-Python: >=3.6
